pySCOrchestrator/__init__.py
pySCOrchestrator-0.0.3.dist-info/LICENSE
pySCOrchestrator-0.0.3.dist-info/METADATA
pySCOrchestrator-0.0.3.dist-info/WHEEL
pySCOrchestrator-0.0.3.dist-info/top_level.txt
pySCOrchestrator-0.0.3.dist-info/RECORD
