Metadata-Version: 2.1
Name: pySCOrchestrator
Version: 0.0.3
Summary: A simple client for calling System Center Orchestrator runbooks in python
Home-page: https://github.com/davidwallis3101/pySCOrchestrator
Author: davidwallis
Author-email: david@wallis2000.co.uk
License: Apache License
License-File: LICENSE
Requires-Dist: requests >=2.0.0
Requires-Dist: requests-ntlm
Requires-Dist: xmltodict
